setup.py
bancommons.egg-info/PKG-INFO
bancommons.egg-info/SOURCES.txt
bancommons.egg-info/dependency_links.txt
bancommons.egg-info/top_level.txt
generate/__init__.py
generate/application.py
generate/generate_code_service.py