Metadata-Version: 1.0
Name: bancommons
Version: 0.0.1
Summary: 36ban commons
Home-page: http://liluo.org
Author: zhaowenlei
Author-email: zhaowenlei789@sina.com
License: MIT License
Keywords: ban,commons
Platform: any
